LICENSE
README.md
setup.cfg
setup.py
blockchain_parser/__init__.py
blockchain_parser/address.py
blockchain_parser/block.py
blockchain_parser/block_header.py
blockchain_parser/blockchain.py
blockchain_parser/index.py
blockchain_parser/input.py
blockchain_parser/output.py
blockchain_parser/script.py
blockchain_parser/transaction.py
blockchain_parser/undo.py
blockchain_parser/utils.py
blockchain_parser/utils_taproot.py
blockchain_parser_1.0.egg-info/PKG-INFO
blockchain_parser_1.0.egg-info/SOURCES.txt
blockchain_parser_1.0.egg-info/dependency_links.txt
blockchain_parser_1.0.egg-info/requires.txt
blockchain_parser_1.0.egg-info/top_level.txt