Metadata-Version: 2.1
Name: blockchain-parser-1.0
Version: 0.2.0
Summary: Bitcoin blockchain parser
Home-page: https://github.com/chainlaboratory/blockchain-parser-1.0
Author: Antoine Le Calvez
Author-email: antoine@p2sh.info
License: UNKNOWN
Platform: UNKNOWN
Classifier: Development Status :: 5 - Production/Stable
Classifier: Environment :: Console
Classifier: Intended Audience :: Developers
Classifier: License :: OSI Approved :: GNU Lesser General Public License v3 (LGPLv3)
Classifier: Topic :: Software Development :: Libraries
License-File: LICENSE
